LICENSE
MANIFEST.in
NOTICE
README.md
setup.cfg
setup.py
apache_flink_libraries.egg-info/PKG-INFO
apache_flink_libraries.egg-info/SOURCES.txt
apache_flink_libraries.egg-info/dependency_links.txt
apache_flink_libraries.egg-info/top_level.txt
deps/bin/bash-java-utils.jar
deps/lib/flink-cep-2.1.0.jar
deps/lib/flink-connector-files-2.1.0.jar
deps/lib/flink-csv-2.1.0.jar
deps/lib/flink-dist-2.1.0.jar
deps/lib/flink-json-2.1.0.jar
deps/lib/flink-scala_2.12-2.1.0.jar
deps/lib/flink-table-api-java-uber-2.1.0.jar
deps/lib/flink-table-planner-loader-2.1.0.jar
deps/lib/flink-table-runtime-2.1.0.jar
deps/lib/log4j-1.2-api-2.24.3.jar
deps/lib/log4j-api-2.24.3.jar
deps/lib/log4j-core-2.24.3.jar
deps/lib/log4j-layout-template-json-2.24.3.jar
deps/lib/log4j-slf4j-impl-2.24.3.jar
deps/licenses/LICENSE.antlr-java-grammar-files
deps/licenses/LICENSE.antlr-runtime
deps/licenses/LICENSE.asm
deps/licenses/LICENSE.automaton
deps/licenses/LICENSE.base64
deps/licenses/LICENSE.google-auth-library-credentials
deps/licenses/LICENSE.grizzled-slf4j
deps/licenses/LICENSE.icu4j
deps/licenses/LICENSE.influx
deps/licenses/LICENSE.janino
deps/licenses/LICENSE.javax.activation
deps/licenses/LICENSE.jaxb
deps/licenses/LICENSE.jline
deps/licenses/LICENSE.jsr166y
deps/licenses/LICENSE.jzlib
deps/licenses/LICENSE.kryo
deps/licenses/LICENSE.minlog
deps/licenses/LICENSE.protobuf
deps/licenses/LICENSE.py4j
deps/licenses/LICENSE.pyrolite
deps/licenses/LICENSE.scala
deps/licenses/LICENSE.slf4j-api
deps/licenses/LICENSE.webbit
deps/opt/flink-python-2.1.0.jar
deps/opt/flink-sql-client-2.1.0.jar
deps/plugins/README.txt
deps/plugins/external-resource-gpu/flink-external-resource-gpu-2.1.0.jar
deps/plugins/external-resource-gpu/gpu-discovery-common.sh
deps/plugins/external-resource-gpu/nvidia-gpu-discovery.sh
deps/plugins/metrics-datadog/flink-metrics-datadog-2.1.0.jar
deps/plugins/metrics-graphite/flink-metrics-graphite-2.1.0.jar
deps/plugins/metrics-influx/flink-metrics-influxdb-2.1.0.jar
deps/plugins/metrics-jmx/flink-metrics-jmx-2.1.0.jar
deps/plugins/metrics-otel/flink-metrics-otel-2.1.0.jar
deps/plugins/metrics-prometheus/flink-metrics-prometheus-2.1.0.jar
